chess/__init__.py
chess/ai.py
chess/chess.py
chess/game.py
chess/heuristic.py
chess/utils.py
tests/__init__.py
tests/test.py
tests/test_ai.py
tests/test_chess.py
chess_ai-0.4.dist-info/LICENSE
chess_ai-0.4.dist-info/METADATA
chess_ai-0.4.dist-info/WHEEL
chess_ai-0.4.dist-info/top_level.txt
chess_ai-0.4.dist-info/RECORD
