Metadata-Version: 2.1
Name: chess-ai
Version: 0.4
Summary: Provides Chess API and AI
Home-page: http://github.com/thkim1011/chess-ai
Author: Tae Hyung Kim
Author-email: thkim1011@berkeley.edu
License: MIT
Platform: UNKNOWN
Classifier: Programming Language :: Python :: 3
